test.py
pyutils/__init__.py
pyutils/cvfacedetector/__init__.py
pyutils/cvfacedetector/face_detection_yunet_2023mar.onnx
pyutils/cvfacedetector/facedetector.py
pyutils/cvfacedetector/yunet.py
lambda_pyutils-0.2.1.dist-info/LICENSE
lambda_pyutils-0.2.1.dist-info/METADATA
lambda_pyutils-0.2.1.dist-info/WHEEL
lambda_pyutils-0.2.1.dist-info/top_level.txt
lambda_pyutils-0.2.1.dist-info/RECORD
