Metadata-Version: 2.1
Name: lambda-pyutils
Version: 0.2.1
Summary: Python utilities for machine learning
Author-email: Lambda IT <info@lambda-it.ch>
Project-URL: Homepage, https://github.com/Lambda-IT/pyutils
Project-URL: Bug Tracker, https://github.com/Lambda-IT/pyutils/issues
Classifier: Programming Language :: Python :: 3
Classifier: License :: OSI Approved :: MIT License
Classifier: Operating System :: OS Independent
Requires-Python: >=3.7
License-File: LICENSE
